edgar_pack/__init__.py
edgar_pack/lib.py
edgar_pack/data/data.csv.gz
edgar_pack-1.0.data/scripts/edgar_pack-run
tests/__init__.py
tests/lib_test.py
edgar_pack-1.0.dist-info/LICENSE
edgar_pack-1.0.dist-info/METADATA
edgar_pack-1.0.dist-info/WHEEL
edgar_pack-1.0.dist-info/top_level.txt
edgar_pack-1.0.dist-info/RECORD
