Metadata-Version: 2.1
Name: edgar-pack
Version: 1.0
Summary: Project Description
Home-page: UNKNOWN
Author: UNKNOWN
Author-email: UNKNOWN
License: UNKNOWN
Platform: UNKNOWN
